python_unsplash_async-1.0.4.dist-info/METADATA
python_unsplash_async-1.0.4.dist-info/RECORD
python_unsplash_async-1.0.4.dist-info/WHEEL
python_unsplash_async-1.0.4.dist-info/top_level.txt
python_unsplash_async-1.0.4.dist-info/zip-safe
unsplash/__init__.py
unsplash/api.py
unsplash/auth.py
unsplash/client.py
unsplash/collection.py
unsplash/errors.py
unsplash/models.py
unsplash/photo.py
unsplash/search.py
unsplash/stat.py
unsplash/user.py
