Metadata-Version: 2.1
Name: python-unsplash-async
Version: 1.0.4
Summary: A Python client for the Unsplash API.
Home-page: http://github.com/alin23/python-unsplash
Author: Yakup Adaklı
Author-email: yakup.adakli@gmail.com
Maintainer: Alin Panaitiu
Maintainer-email: alin.p32@gmail.com
License: MIT
Keywords: unsplash library
Platform: UNKNOWN
Classifier: Development Status :: 3 - Alpha
Classifier: Topic :: Software Development :: Libraries
Classifier: License :: OSI Approved :: MIT License
Classifier: Operating System :: OS Independent
Classifier: Programming Language :: Python :: 3.5
Classifier: Programming Language :: Python :: 3.6
Requires-Dist: oauthlib (>=2.0.1)
Requires-Dist: requests (>=2.13.0)
Requires-Dist: requests-oauthlib (>=0.7.0)
Requires-Dist: six (>=1.10.0)
Requires-Dist: aiohttp
